colorprint3/__init__.py
colorprint3-1.3a1.dist-info/LICENSE
colorprint3-1.3a1.dist-info/METADATA
colorprint3-1.3a1.dist-info/WHEEL
colorprint3-1.3a1.dist-info/top_level.txt
colorprint3-1.3a1.dist-info/RECORD
