Metadata-Version: 2.1
Name: colorprint3
Version: 1.3a1
Summary: A simple library to print with color and style on Python 3
Author-email: trunghieumickey <trunghieumickey@outlook.com.vn>
License: GNU GENERAL PUBLIC LICENSE
Project-URL: Homepage, https://github.com/trunghieumickey/colorprint3
Project-URL: Bug Tracker, https://github.com/trunghieumickey/colorprint3/issues
Classifier: Programming Language :: Python :: 3
Classifier: License :: OSI Approved :: GNU General Public License v3 or later (GPLv3+)
Requires-Python: >=3.8
License-File: LICENSE
